browser_copilot/__init__.py
browser_copilot/__main__.py
browser_copilot/agent.py
browser_copilot/browser_tools.py
browser_copilot/cli.py
browser_copilot/config_manager.py
browser_copilot/config_wizard.py
browser_copilot/constants.py
browser_copilot/core.py
browser_copilot/reporter.py
browser_copilot/storage_manager.py
browser_copilot/test_enhancer.py
browser_copilot/token_optimizer.py
browser_copilot/verbose_logger.py
browser_copilot/analysis/__init__.py
browser_copilot/analysis/report_parser.py
browser_copilot/cli/__init__.py
browser_copilot/cli/commands.py
browser_copilot/cli/executor.py
browser_copilot/cli/parser.py
browser_copilot/cli/utils.py
browser_copilot/context_management/README.md
browser_copilot/context_management/__init__.py
browser_copilot/context_management/analyzer.py
browser_copilot/context_management/base.py
browser_copilot/context_management/hooks.py
browser_copilot/context_management/metrics.py
browser_copilot/context_management/token_utils.py
browser_copilot/context_management/algorithms/__init__.py
browser_copilot/context_management/algorithms/sliding_window_algorithm.py
browser_copilot/context_management/strategies/__init__.py
browser_copilot/context_management/strategies/base.py
browser_copilot/context_management/strategies/no_op.py
browser_copilot/context_management/strategies/sliding_window.py
browser_copilot/context_management/strategies/smart_trim.py
browser_copilot/hil_detection/__init__.py
browser_copilot/hil_detection/ask_human_tool.py
browser_copilot/io/__init__.py
browser_copilot/io/input_handler.py
browser_copilot/io/output_handler.py
browser_copilot/io/stream_handler.py
browser_copilot/models/__init__.py
browser_copilot/models/base.py
browser_copilot/models/execution.py
browser_copilot/models/metrics.py
browser_copilot/models/py.typed
browser_copilot/models/results.py
browser_copilot/models/serialization.py
browser_copilot/prompts/__init__.py
browser_copilot/prompts/builder.py
browser_copilot/utils/__init__.py
browser_copilot-1.2.3.dist-info/METADATA
browser_copilot-1.2.3.dist-info/WHEEL
browser_copilot-1.2.3.dist-info/entry_points.txt
browser_copilot-1.2.3.dist-info/licenses/LICENSE
browser_copilot-1.2.3.dist-info/RECORD
