Metadata-Version: 2.4
Name: browser-copilot
Version: 1.2.3
Summary: AI-powered browser automation copilot for testing
Project-URL: Homepage, https://github.com/smiao-icims/browser-copilot
Project-URL: Bug Reports, https://github.com/smiao-icims/browser-copilot/issues
Project-URL: Documentation, https://github.com/smiao-icims/browser-copilot#readme
Project-URL: Source, https://github.com/smiao-icims/browser-copilot
Author-email: Browser Copilot Team <smiao-icims@icims.com>
License: MIT
License-File: LICENSE
Keywords: ai,automation,browser,llm,playwright,testing
Classifier: Development Status :: 4 - Beta
Classifier: Intended Audience :: Developers
Classifier: License :: OSI Approved :: MIT License
Classifier: Programming Language :: Python :: 3
Classifier: Programming Language :: Python :: 3.11
Classifier: Programming Language :: Python :: 3.12
Classifier: Topic :: Software Development :: Quality Assurance
Classifier: Topic :: Software Development :: Testing
Requires-Python: >=3.11
Requires-Dist: jinja2<3.1
Requires-Dist: langchain-mcp-adapters>=0.1.0
Requires-Dist: langchain>=0.2.0
Requires-Dist: langgraph>=0.1.0
Requires-Dist: markupsafe<3.0
Requires-Dist: mcp>=0.1.0
Requires-Dist: model-forge-llm>=2.2.2
Requires-Dist: pyyaml>=6.0
Requires-Dist: questionary>=2.0.0
Provides-Extra: dev
Requires-Dist: bandit>=1.7.0; extra == 'dev'
Requires-Dist: black>=23.0; extra == 'dev'
Requires-Dist: flake8>=6.0; extra == 'dev'
Requires-Dist: isort>=5.0; extra == 'dev'
Requires-Dist: mypy>=1.0; extra == 'dev'
Requires-Dist: pre-commit>=3.0; extra == 'dev'
Requires-Dist: pytest-asyncio>=0.21; extra == 'dev'
Requires-Dist: pytest-cov>=4.0; extra == 'dev'
Requires-Dist: pytest>=7.0; extra == 'dev'
Requires-Dist: ruff>=0.1.0; extra == 'dev'
Requires-Dist: safety>=2.0.0; extra == 'dev'
Requires-Dist: twine>=4.0.0; extra == 'dev'
Provides-Extra: dotenv
Requires-Dist: python-dotenv>=1.0.0; extra == 'dotenv'
